{
  "$schema": "./node_modules/@angular/service-worker/config/schema.json",
  "index": "/index.html",
  "assetGroups": [
    {
      "name": "app",
      "installMode": "prefetch",
      "resources": {
        "files": [
          "/favicon.ico",
          "/index.html",
          "/manifest.webmanifest",
          "/*.css",
          "/*.js"
        ],
        "urls": [ 
          "https://tdrobinson94.github.io/Cal_App_t1a_8_24_20/#/calendar",
          "https://tdrobinson94.github.io/Cal_App_t1a_8_24_20/#/profile",
          "https://tdrobinson94.github.io/Cal_App_t1a_8_24_20/#/settings",
          "https://tdrobinson94.github.io/Cal_App_t1a_8_24_20/#/login",
          "https://tdrobinson94.github.io/Cal_App_t1a_8_24_20/#/signup"
        ]
      }
    },
    {
      "name": "assets",
      "installMode": "lazy",
      "updateMode": "prefetch",
      "resources": {
        "files": [
          "/assets/**",
          "/*.(eot|svg|cur|jpg|png|webp|gif|otf|ttf|woff|woff2|ani)"
        ]
      }
    }
  ]
}
